automator/Cleaner.py
automator/__init__.py
automator/version.py
automator-0.1.0.dist-info/DESCRIPTION.rst
automator-0.1.0.dist-info/METADATA
automator-0.1.0.dist-info/RECORD
automator-0.1.0.dist-info/WHEEL
automator-0.1.0.dist-info/metadata.json
automator-0.1.0.dist-info/top_level.txt
